ppcalendar/__init__.py
ppcalendar/events.py
ppcalendar/main.py
ppcalendar/ppcalendar.py
ppcalendar-0.2.5.dist-info/licenses/LICENSE
ppcalendar-0.2.5.dist-info/METADATA
ppcalendar-0.2.5.dist-info/WHEEL
ppcalendar-0.2.5.dist-info/entry_points.txt
ppcalendar-0.2.5.dist-info/top_level.txt
ppcalendar-0.2.5.dist-info/RECORD
