Metadata-Version: 2.4
Name: ppcalendar
Version: 0.2.5
Summary: Beautiful terminal calendar with seasonal colors
Author-email: Sergey Samoylov <linews@yandex.ru>
License: GPL-3.0-or-later
Classifier: Development Status :: 4 - Beta
Classifier: Environment :: Console
Classifier: Intended Audience :: Developers
Classifier: Programming Language :: Python :: 3
Requires-Python: >=3.8
License-File: LICENSE
Dynamic: license-file
